safeheron_api_sdk_python/client.py
safeheron_api_sdk_python/tools.py
safeheron_api_sdk_python/api/account_api.py
safeheron_api_sdk_python/api/api_key_management_api.py
safeheron_api_sdk_python/api/coin_api.py
safeheron_api_sdk_python/api/compliance_api.py
safeheron_api_sdk_python/api/gas_api.py
safeheron_api_sdk_python/api/mpc_sign_api.py
safeheron_api_sdk_python/api/tools_api.py
safeheron_api_sdk_python/api/transaction_api.py
safeheron_api_sdk_python/api/web3_api.py
safeheron_api_sdk_python/api/webhook_api.py
safeheron_api_sdk_python/api/whitelist_api.py
safeheron_api_sdk_python/cosigner/co_signer_converter.py
safeheron_api_sdk_python/webhook/webhook_converter.py
safeheron_api_sdk_python-1.1.22.dist-info/licenses/LICENSE
safeheron_api_sdk_python-1.1.22.dist-info/METADATA
safeheron_api_sdk_python-1.1.22.dist-info/WHEEL
safeheron_api_sdk_python-1.1.22.dist-info/top_level.txt
safeheron_api_sdk_python-1.1.22.dist-info/RECORD
