Metadata-Version: 2.4
Name: safeheron_api_sdk_python
Version: 1.1.22
Summary: Python for Safeheron API
Home-page: https://github.com/Safeheron/safeheron-api-sdk-python
Author: safeheron
Author-email: support@safeheron.com
License: MIT License
Platform: all
Classifier: Operating System :: OS Independent
Classifier: Programming Language :: Python :: 3
License-File: LICENSE
Requires-Dist: pycryptodomex
Requires-Dist: requests
Requires-Dist: cryptography
Dynamic: author
Dynamic: author-email
Dynamic: classifier
Dynamic: description
Dynamic: home-page
Dynamic: license
Dynamic: license-file
Dynamic: platform
Dynamic: requires-dist
Dynamic: summary
